SpinalHDL/src/test/python/usecocotb/logicorReg.v
// Generator : SpinalHDL v1.8.1    git head : 2a7592004363e5b40ec43e1f122ed8641cd8965b
// Component : logicorReg
// Git hash  : 7b7bc2e83298c4a8781e05e7da5b2bc64558d35c

`timescale 1ns/1ps

module logicorReg (
  input               a,
  input      [2:0]    b,
  output reg [2:0]    output_1,
  input               clk,
  input               reset
);

  reg        [2:0]    reg1;
  reg                 reg3;
  wire                when_logicorReg_l21;

  assign when_logicorReg_l21 = (! a);
  always @(*) begin
    output_1 = 3'b000;
    if(a) begin
      output_1 = (b + b);
    end
  end

  always @(posedge clk or posedge reset) begin
    if(reset) begin
      reg1 <= 3'b000;
    end else begin
      reg1 <= b;
    end
  end

  always @(posedge clk) begin
    if(a) begin
      reg3 <= 1'b1;
    end
    if(when_logicorReg_l21) begin
      reg3 <= 1'b0;
    end
  end

  `ifdef COCOTB_SIM
initial begin
  $dumpfile ("logicorReg.vcd");
  $dumpvars (0, logicorReg);
  #1;
end
`endif
endmodule

SpinalHDL/src/test/python/usecocotb/logicorReg.vcd
$date
	Tue Jun 13 20:08:57 2023
$end
$version
	Icarus Verilog
$end
$timescale
	1ps
$end
$scope module logicorReg $end
$var wire 1 ! a $end
$var wire 3 " b [2:0] $end
$var wire 1 # clk $end
$var wire 1 $ reset $end
$var wire 1 % when_logicorReg_l21 $end
$var reg 3 & output_1 [2:0] $end
$var reg 3 ' reg1 [2:0] $end
$var reg 1 ( reg3 $end
$upscope $end
$enddefinitions $end
#0
$dumpvars
0(
b0 '
b0 &
1%
z$
1#
b0 "
0!
$end
#500
b10 &
b1 "
0%
1!
0#
#1000
1(
b1 '
1#
#1500
b0 &
b0 "
1%
0!
0#
#2000
0(
b0 '
1#
#2500
0#
#3000
1#
#3500
b10 &
b1 "
0%
1!
0#
#4000
1(
b1 '
1#
#4500
0#
#5000
1#
#5500
b0 &
b0 "
1%
0!
0#
#6000
0(
b0 '
1#
#6500
b10 &
b1 "
0%
1!
0#
#7000
1(
b1 '
1#
#7500
b0 &
b0 "
1%
0!
0#
#8000
0(
b0 '
1#
#8500
0#
#9000
1#
#9500
0#
#10000
1#
#10500
0#
#11000
1#
#11500
0#
#12000
1#
#12500
b10 &
b1 "
0%
1!
0#
#13000
1(
b1 '
1#
#13500
b0 &
b0 "
1%
0!
0#
#14000
0(
b0 '
1#
#14500
b10 &
b1 "
0%
1!
0#
#15000
1(
b1 '
1#
#15500
0#
#16000
1#
#16500
b0 &
b0 "
1%
0!
0#
#17000
0(
b0 '
1#
#17500
b10 &
b1 "
0%
1!
0#
#18000
1(
b1 '
1#
#18500
b0 &
b0 "
1%
0!
0#
#19000
0(
b0 '
1#
#19500
b10 &
b1 "
0%
1!
0#
#20000
1(
b1 '
1#
#20500
b0 &
b0 "
1%
0!
0#
#21000
0(
b0 '
1#
#21500
0#
#22000
1#
#22500
b10 &
b1 "
0%
1!
0#
#23000
1(
b1 '
1#
#23500
b0 &
b0 "
1%
0!
0#
#24000
0(
b0 '
1#
#24500
b10 &
b1 "
0%
1!
0#
#25000
1(
b1 '
1#
#25500
0#
#26000
1#
#26500
0#
#27000
1#
#27500
b0 &
b0 "
1%
0!
0#
#28000
0(
b0 '
1#
#28500
0#
#29000
1#
#29500
0#
#30000
1#
#30500
b10 &
b1 "
0%
1!
0#
#31000
1(
b1 '
1#
#31500
b0 &
b0 "
1%
0!
0#
#32000
0(
b0 '
1#
#32500
0#
#33000
1#
#33500
b10 &
b1 "
0%
1!
0#
#34000
1(
b1 '
1#
#34500
b0 &
b0 "
1%
0!
0#
#35000
0(
b0 '
1#
#35500
b10 &
b1 "
0%
1!
0#
#36000
1(
b1 '
1#
#36500
b0 &
b0 "
1%
0!
0#
#37000
0(
b0 '
1#
#37500
0#
#38000
1#
#38500
0#
#39000
1#
#39500
b10 &
b1 "
0%
1!
0#
#40000
1(
b1 '
1#
#40500
b0 &
b0 "
1%
0!
0#
#41000
0(
b0 '
1#
#41500
b10 &
b1 "
0%
1!
0#
#42000
1(
b1 '
1#
#42500
0#
#43000
1#
#43500
b0 &
b0 "
1%
0!
0#
#44000
0(
b0 '
1#
#44500
b10 &
b1 "
0%
1!
0#
#45000
1(
b1 '
1#
#45500
0#
#46000
1#
#46500
b0 &
b0 "
1%
0!
0#
#47000
0(
b0 '
1#
#47500
b10 &
b1 "
0%
1!
0#
#48000
1(
b1 '
1#
#48500
b0 &
b0 "
1%
0!
0#
#49000
0(
b0 '
1#
#49500
b10 &
b1 "
0%
1!
0#
#50000
1(
b1 '
1#
#50500
b0 &
b0 "
1%
0!
0#
#51000
0(
b0 '
1#
#51500
b10 &
b1 "
0%
1!
0#
#52000
1(
b1 '
1#
#52500
b0 &
b0 "
1%
0!
0#
#53000
0(
b0 '
1#
#53500
0#
#54000
1#
#54500
0#
#55000
1#
#55500
b10 &
b1 "
0%
1!
0#
#56000
1(
b1 '
1#
#56500
b0 &
b0 "
1%
0!
0#
#57000
0(
b0 '
1#
#57500
0#
#58000
1#
#58500
0#
#59000
1#
#59500
0#
#60000
1#
#60500
0#
#61000
1#
#61500
b10 &
b1 "
0%
1!
0#
#62000
1(
b1 '
1#
#62500
b0 &
b0 "
1%
0!
0#
#63000
0(
b0 '
1#
#63500
b10 &
b1 "
0%
1!
0#
#64000
1(
b1 '
1#
#64500
0#
#65000
1#
#65500
b0 &
b0 "
1%
0!
0#
#66000
0(
b0 '
1#
#66500
0#
#67000
1#
#67500
b10 &
b1 "
0%
1!
0#
#68000
1(
b1 '
1#
#68500
b0 &
b0 "
1%
0!
0#
#69000
0(
b0 '
1#
#69500
b10 &
b1 "
0%
1!
0#
#70000
1(
b1 '
1#
#70500
b0 &
b0 "
1%
0!
0#
#71000
0(
b0 '
1#
#71500
0#
#72000
1#
#72500
b10 &
b1 "
0%
1!
0#
#73000
1(
b1 '
1#
#73500
b0 &
b0 "
1%
0!
0#
#74000
0(
b0 '
1#
#74500
b10 &
b1 "
0%
1!
0#
#75000
1(
b1 '
1#
#75500
b0 &
b0 "
1%
0!
0#
#76000
0(
b0 '
1#
#76500
0#
#77000
1#
#77500
0#
#78000
1#
#78500
b10 &
b1 "
0%
1!
0#
#79000
1(
b1 '
1#
#79500
b0 &
b0 "
1%
0!
0#
#80000
0(
b0 '
1#
#80500
0#
#81000
1#
#81500
b10 &
b1 "
0%
1!
0#
#82000
1(
b1 '
1#
#82500
0#
#83000
1#
#83500
b0 &
b0 "
1%
0!
0#
#84000
0(
b0 '
1#
#84500
0#
#85000
1#
#85500
b10 &
b1 "
0%
1!
0#
#86000
1(
b1 '
1#
#86500
0#
#87000
1#
#87500
b0 &
b0 "
1%
0!
0#
#88000
0(
b0 '
1#
#88500
0#
#89000
1#
#89500
b10 &
b1 "
0%
1!
0#
#90000
1(
b1 '
1#
#90500
b0 &
b0 "
1%
0!
0#
#91000
0(
b0 '
1#
#91500
b10 &
b1 "
0%
1!
0#
#92000
1(
b1 '
1#
#92500
0#
#93000
1#
#93500
0#
#94000
1#
#94500
b0 &
b0 "
1%
0!
0#
#95000
0(
b0 '
1#
#95500
b10 &
b1 "
0%
1!
0#
#96000
1(
b1 '
1#
#96500
b0 &
b0 "
1%
0!
0#
#97000
0(
b0 '
1#
#97500
b10 &
b1 "
0%
1!
0#
#98000
1(
b1 '
1#
